itaed/__init__.py
itaed/click.py
itaed/exception.py
itaed/select.py
itaed/tools.py
itaed-0.1.1.dist-info/METADATA
itaed-0.1.1.dist-info/WHEEL
itaed-0.1.1.dist-info/top_level.txt
itaed-0.1.1.dist-info/RECORD
