Metadata-Version: 2.1
Name: itaed
Version: 0.1.1
Summary: My first Python library
Home-page: UNKNOWN
Author: Me
Author-email: UNKNOWN
License: MIT
Platform: UNKNOWN
